crowd/__init__.py
crowd/backends.py
crowd/middleware.py
crowd/models.py
django_crowd_sso-0.58.dist-info/DESCRIPTION.rst
django_crowd_sso-0.58.dist-info/LICENSE.txt
django_crowd_sso-0.58.dist-info/METADATA
django_crowd_sso-0.58.dist-info/RECORD
django_crowd_sso-0.58.dist-info/WHEEL
django_crowd_sso-0.58.dist-info/metadata.json
django_crowd_sso-0.58.dist-info/top_level.txt
