Metadata-Version: 2.0
Name: django-crowd-sso
Version: 0.58
Summary: Atlassian Crowd integration for Django with SSO
Home-page: https://github.com/WFP-BKK/django-crowd-sso
Author: Tobias Carlander
Author-email: tobias.carlander@wfp.org
License: Creative Commons Attribution-Noncommercial-Share Alike license
Keywords: django crowd users authentication sso
Platform: UNKNOWN
Classifier: Development Status :: 4 - Beta
Classifier: Intended Audience :: Developers
Classifier: Programming Language :: Python :: 3
Classifier: Programming Language :: Python :: 3 :: Only
Classifier: Programming Language :: Python :: 3.4
Classifier: Programming Language :: Python :: 3.5
Classifier: Programming Language :: Python :: 3.6
Requires-Dist: django
Requires-Dist: requests
Requires-Dist: simplejson
